MANIFEST.in
README.rst
setup.py
google/__init__.py
google/proto/__init__.py
google/proto/streetview/__init__.py
google/proto/streetview/publish/__init__.py
google/proto/streetview/publish/v1/__init__.py
google/proto/streetview/publish/v1/resources_pb2.py
google/proto/streetview/publish/v1/resources_pb2_grpc.py
google/proto/streetview/publish/v1/rpcmessages_pb2.py
google/proto/streetview/publish/v1/rpcmessages_pb2_grpc.py
google/proto/streetview/publish/v1/streetview_publish_pb2.py
google/proto/streetview/publish/v1/streetview_publish_pb2_grpc.py
proto_google_maps_streetview_publish_v1.egg-info/PKG-INFO
proto_google_maps_streetview_publish_v1.egg-info/SOURCES.txt
proto_google_maps_streetview_publish_v1.egg-info/dependency_links.txt
proto_google_maps_streetview_publish_v1.egg-info/namespace_packages.txt
proto_google_maps_streetview_publish_v1.egg-info/requires.txt
proto_google_maps_streetview_publish_v1.egg-info/top_level.txt